streamz_nats/__init__.py
streamz_nats/sinks.py
streamz_nats/sources.py
streamz_nats-0.1.0.dist-info/METADATA
streamz_nats-0.1.0.dist-info/WHEEL
streamz_nats-0.1.0.dist-info/entry_points.txt
streamz_nats-0.1.0.dist-info/RECORD
