Metadata-Version: 2.1
Name: streamz-nats
Version: 0.1.0
Summary: 
Home-page: https://github.com/MarekWadinger/streamz_nats
Keywords: streamz,nats
Author: Marek Wadinger
Author-email: marekwadinger@icloud.com
Requires-Python: >=3.7.2,<4.0.0
Classifier: License :: OSI Approved :: MIT License
Classifier: Operating System :: OS Independent
Classifier: Programming Language :: Python :: 3
Classifier: Programming Language :: Python :: 3.8
Classifier: Programming Language :: Python :: 3.9
Classifier: Programming Language :: Python :: 3.10
Classifier: Programming Language :: Python :: 3.11
Classifier: Programming Language :: Python :: 3
Requires-Dist: nats-py (>=2.4.0,<3.0.0)
Requires-Dist: streamz (>=0.6.4,<0.7.0)
Project-URL: Repository, https://github.com/MarekWadinger/streamz_nats
